{
  "project_info": {
    "project_number": "457206831913",
    "firebase_url": "https://ms-push-e0b66.firebaseio.com",
    "project_id": "ms-push-e0b66",
    "storage_bucket": "ms-push-e0b66.appspot.com"
  },
  "client": [
    {
      "client_info": {
        "mobilesdk_app_id": "1:457206831913:android:7a71c7cc8c1e774ea97538",
        "android_client_info": {
          "package_name": "com.cheetahdigital.push"
        }
      },
      "oauth_client": [
        {
          "client_id": "457206831913-iouuebb3cg6itg1oenqea8587nkd0ck9.apps.googleusercontent.com",
          "client_type": 1,
          "android_info": {
            "package_name": "com.cheetahdigital.push",
            "certificate_hash": "966f69c27c0b5f50c82635cfcc5c1c6a9826699d"
          }
        },
        {
          "client_id": "457206831913-mk5s2ons4hk8dpkq6r7b4q5e53dmbe2l.apps.googleusercontent.com",
          "client_type": 3
        }
      ],
      "api_key": [
        {
          "current_key": "AIzaSyB5WRJWXbNUfY0x7E-5pgrsssV6oVlYflk"
        }
      ],
      "services": {
        "appinvite_service": {
          "other_platform_oauth_client": [
            {
              "client_id": "457206831913-mk5s2ons4hk8dpkq6r7b4q5e53dmbe2l.apps.googleusercontent.com",
              "client_type": 3
            }
          ]
        }
      }
    }
  ],
  "configuration_version": "1"
}